nvw/.gitignore
nvw/__init__.py
nvw/app1/__init__.py
nvw/app1/admin.py
nvw/app1/apps.py
nvw/app1/common.py
nvw/app1/consumers.py
nvw/app1/migrations/__init__.py
nvw/app1/models.py
nvw/app1/protobuf/__init__.py
nvw/app1/protobuf/device_pb2.py
nvw/app1/protobuf/device_pb2_grpc.py
nvw/app1/rest/__init__.py
nvw/app1/rest/urls.py
nvw/app1/serializers.py
nvw/app1/static/favicon.ico
nvw/app1/static/index.html
nvw/app1/static/js/bundle.js
nvw/app1/static/js/bundle.js.map
nvw/app1/tests.py
nvw/app1/utils.py
nvw/app1/views.py
nvw/config/__init__.py
nvw/config/asgi.py
nvw/config/settings.py
nvw/config/urls.py
nvw/config/wsgi.py
nvw/manage.py
nvw/media/dummy
nvw/settings-template.py
nvw-1.0.4.dist-info/LICENSE
nvw-1.0.4.dist-info/METADATA
nvw-1.0.4.dist-info/WHEEL
nvw-1.0.4.dist-info/entry_points.txt
nvw-1.0.4.dist-info/RECORD
